nisqoptml/__init__.py
nisqoptml/distribute.py
nisqoptml/explain.py
nisqoptml/mitigate.py
nisqoptml/qnn.py
nisqoptml/utils.py
nisqoptml-0.1.1.dist-info/METADATA
nisqoptml-0.1.1.dist-info/WHEEL
nisqoptml-0.1.1.dist-info/licenses/LICENSE
nisqoptml-0.1.1.dist-info/licenses/NOTICE
nisqoptml-0.1.1.dist-info/RECORD
