Metadata-Version: 2.4
Name: nisqoptml
Version: 0.1.1
Summary: NISQ-Optimized Machine Learning: Noise-resilient QML library with Federated and DP Support
License: Apache-2.0
License-File: LICENSE
License-File: NOTICE
Keywords: quantum,machine-learning,qml,nisq,federated-learning,differential-privacy
Author: Venkata Vikhyat Choppa
Author-email: venkata_choppa@outlook.com
Requires-Python: >=3.8,<4.0
Classifier: License :: OSI Approved :: Apache Software License
Classifier: Operating System :: OS Independent
Classifier: Programming Language :: Python :: 3
Classifier: Programming Language :: Python :: 3.8
Classifier: Programming Language :: Python :: 3.9
Classifier: Programming Language :: Python :: 3.10
Classifier: Programming Language :: Python :: 3.11
Classifier: Programming Language :: Python :: 3.12
Classifier: Programming Language :: Python :: 3.13
Classifier: Programming Language :: Python :: 3.14
Classifier: Topic :: Scientific/Engineering :: Artificial Intelligence
Classifier: Topic :: Scientific/Engineering :: Physics
Requires-Dist: matplotlib (>=3.5,<4.0)
Requires-Dist: mpi4py (>=3.1,<4.0)
Requires-Dist: pennylane (>=0.30,<0.31)
Requires-Dist: qiskit (>=1.0,<2.0)
Requires-Dist: qiskit-aer (>=0.12,<0.13)
Requires-Dist: sympy (>=1.10,<2.0)
Requires-Dist: torch (>=2.0,<3.0)
